{
  "Variable ocean.bigthetao.tavg-ol-hm-sea.mon.GLB (Omon.bigthetaoga)": {
    "HadGEM3-GC5": "onm/grid-T`: `<field field_ref=\"toce_con\" name=\"bigthetao\" operation=\"average\" freq_op=\"1mo\" > @toce_con_e3t / @e3t </field>` <br> `onm/grid-T`: `<field field_ref=\"e3t\" name=\"thkcello\" />"
  },
  "Variable ocean.bigthetao.tavg-ol-hxy-sea.mon.GLB (Omon.bigthetao)": {
    "HadGEM3-GC5": "onm/grid-T`: `<field field_ref=\"toce_con\" name=\"bigthetao\" operation=\"average\" freq_op=\"1mo\" > @toce_con_e3t / @e3t </field>"
  },
  "Variable ocean.bigthetao.tavg-op20bar-hxy-sea.day.GLB (Oday.bigthetao200)": {
    "HadGEM3-GC5": "ond/grid-T`: `<field field_ref=\"toce_con\" name=\"bigthetao\" operation=\"average\" freq_op=\"1d\" > @toce_con_e3t / @e3t </field>"
  },
  "Variable ocean.diftrblo.tavg-ol-hxy-sea.yr.GLB (Oyr.diftrblo)": {
    "HadGEM3-GC31": "onm/grid-W`: `<field field_ref=\"aht2d_eiv\" name=\"diftrblo\" />",
    "UKESM1": "onm/grid-W`: `<field field_ref=\"aht2d_eiv\" name=\"diftrblo\" />",
    "UKESM1-3": "onm/grid-W`: `<field field_ref=\"aht2d_eiv\" name=\"diftrblo\" />"
  },
  "Variable ocean.difvho.tavg-ol-hxy-sea.yr.GLB (Oyr.difvho)": {
    "HadGEM3-GC31": "onm/grid-W`: `<field field_ref=\"avt\" name=\"difvho\" />",
    "HadGEM3-GC5": "onm/grid-W`: `<field field_ref=\"avt\" name=\"difvho\" />",
    "UKESM1": "onm/grid-W`: `<field field_ref=\"avt\" name=\"difvho\" />",
    "UKESM1-3": "onm/grid-W`: `<field field_ref=\"avt\" name=\"difvho\" />"
  },
  "Variable ocean.difvso.tavg-ol-hxy-sea.yr.GLB (Oyr.difvso)": {
    "HadGEM3-GC31": "onm/grid-W`: `<field field_ref=\"avs\" name=\"difvso\" />",
    "HadGEM3-GC5": "onm/grid-W`: `<field field_ref=\"avs\" name=\"difvso\" />",
    "UKESM1": "onm/grid-W`: `<field field_ref=\"avs\" name=\"difvso\" />",
    "UKESM1-3": "onm/grid-W`: `<field field_ref=\"avs\" name=\"difvso\" />"
  },
  "Variable ocean.dispkexyfo.tavg-u-hxy-sea.yr.GLB (Oyr.dispkexyfo)": {
    "HadGEM3-GC31": "onm/grid-T`: `<field field_ref=\"ketrd_ldf_vsum\" name=\"dispkexyfo\" />",
    "UKESM1": "onm/grid-T`: `<field field_ref=\"ketrd_ldf_vsum\" name=\"dispkexyfo\" />",
    "UKESM1-3": "onm/grid-T`: `<field field_ref=\"ketrd_ldf_vsum\" name=\"dispkexyfo\" />"
  },
  "Variable ocean.evspsbl.tavg-u-hxy-ifs.mon.GLB (Omon.evs)": {
    "HadGEM3-GC31": "onm/grid-T`: `<field field_ref=\"evap_ao_cea\" name=\"evs\" />` <br> `onm/grid-T`: `<field field_ref=\"empmr\" />` <br> `onm/grid-T`: `<field field_ref=\"berg_total_melt\" />` <br> `onm/grid-T`: `<field field_ref=\"runoffs\" name=\"friver\" />` <br> `onm/grid-T`: `<field field_ref=\"snow_ao_cea\" />` <br> `onm/grid-T`: `<field field_ref=\"rain_ao_cea\" />` <br> `onm/grid-T`: `<field field_ref=\"fmmflx\" name=\"fsitherm\" />",
    "HadGEM3-GC5": "onm/grid-T`: `<field field_ref=\"evap_ao_cea\" name=\"evs\" />` <br> `onm/grid-T`: `<field field_ref=\"empmr\" />` <br> `onm/grid-T`: `<field field_ref=\"berg_melt\" name=\"berg_total_melt\" />` <br> `onm/grid-T`: `<field field_ref=\"runoffs\" name=\"friver\" />` <br> `onm/grid-T`: `<field field_ref=\"snow_ao_cea\" />` <br> `onm/grid-T`: `<field field_ref=\"rain_ao_cea\" />` <br> `onm/grid-T`: `<field field_ref=\"fmmflx\" name=\"fsitherm\" />",
    "UKESM1": "onm/grid-T`: `<field field_ref=\"evap_ao_cea\" name=\"evs\" />` <br> `onm/grid-T`: `<field field_ref=\"empmr\" />` <br> `onm/grid-T`: `<field field_ref=\"berg_total_melt\" />` <br> `onm/grid-T`: `<field field_ref=\"runoffs\" name=\"friver\" />` <br> `onm/grid-T`: `<field field_ref=\"snow_ao_cea\" />` <br> `onm/grid-T`: `<field field_ref=\"rain_ao_cea\" />` <br> `onm/grid-T`: `<field field_ref=\"fmmflx\" name=\"fsitherm\" />",
    "UKESM1-3": "onm/grid-T`: `<field field_ref=\"evap_ao_cea\" name=\"evs\" />` <br> `onm/grid-T`: `<field field_ref=\"empmr\" />` <br> `onm/grid-T`: `<field field_ref=\"berg_total_melt\" />` <br> `onm/grid-T`: `<field field_ref=\"runoffs\" name=\"friver\" />` <br> `onm/grid-T`: `<field field_ref=\"snow_ao_cea\" />` <br> `onm/grid-T`: `<field field_ref=\"rain_ao_cea\" />` <br> `onm/grid-T`: `<field field_ref=\"fmmflx\" name=\"fsitherm\" />"
  },
  "Variable ocean.ficeberg.tavg-ol-hxy-sea.3hr.GLB (3hr.ficeberg)": {
    "HadGEM3-GC31": "on3/grid-T`: `<field field_ref=\"berg_total_melt\" />` <br> `on3/grid-T`: `<field field_ref=\"fwfisf3d\" />",
    "HadGEM3-GC5": "on3/grid-T`: `<field field_ref=\"fwfisf3d\" />",
    "UKESM1": "on3/grid-T`: `<field field_ref=\"berg_total_melt\" />` <br> `on3/grid-T`: `<field field_ref=\"fwfisf3d\" />",
    "UKESM1-3": "on3/grid-T`: `<field field_ref=\"berg_total_melt\" />` <br> `on3/grid-T`: `<field field_ref=\"fwfisf3d\" />"
  },
  "Variable ocean.ficeberg.tavg-ol-hxy-sea.mon.GLB (Omon.ficeberg)": {
    "HadGEM3-GC31": "onm/grid-T`: `<field field_ref=\"berg_total_melt\" />` <br> `onm/grid-T`: `<field field_ref=\"fwfisf3d\" />",
    "HadGEM3-GC5": "onm/grid-T`: `<field field_ref=\"fwfisf3d\" />",
    "UKESM1": "onm/grid-T`: `<field field_ref=\"berg_total_melt\" />` <br> `onm/grid-T`: `<field field_ref=\"fwfisf3d\" />",
    "UKESM1-3": "onm/grid-T`: `<field field_ref=\"berg_total_melt\" />` <br> `onm/grid-T`: `<field field_ref=\"fwfisf3d\" />"
  },
  "Variable ocean.flandice.tavg-u-hxy-sea.3hr.GLB (3hr.flandice)": {
    "HadGEM3-GC31": "on3/grid-T`: `<field field_ref=\"fwfisf\" name=\"flandice\" > -1 * @fwfisf </field> ",
    "HadGEM3-GC5": "on3/grid-T`: `<field field_ref=\"fwfisf\" name=\"flandice\" > -1 * @fwfisf </field> ",
    "UKESM1": "on3/grid-T`: `<field field_ref=\"fwfisf\" name=\"flandice\" > -1 * @fwfisf </field> ",
    "UKESM1-3": "on3/grid-T`: `<field field_ref=\"fwfisf\" name=\"flandice\" > -1 * @fwfisf </field> "
  },
  "Variable ocean.flandice.tavg-u-hxy-sea.mon.GLB (Emon.flandice)": {
    "HadGEM3-GC31": "onm/grid-T`: `<field field_ref=\"fwfisf\" name=\"flandice\" > -1 * @fwfisf </field> ",
    "HadGEM3-GC5": "onm/grid-T`: `<field field_ref=\"fwfisf\" name=\"flandice\" > -1 * @fwfisf </field> ",
    "UKESM1": "onm/grid-T`: `<field field_ref=\"fwfisf\" name=\"flandice\" > -1 * @fwfisf </field> ",
    "UKESM1-3": "onm/grid-T`: `<field field_ref=\"fwfisf\" name=\"flandice\" > -1 * @fwfisf </field> "
  },
  "Variable ocean.friver.tavg-u-hxy-sea.3hr.GLB (3hr.friver)": {
    "HadGEM3-GC31": "on3/grid-T`: `<field field_ref=\"runoffs\" name=\"friver\" />",
    "HadGEM3-GC5": "on3/grid-T`: `<field field_ref=\"runoffs\" name=\"friver\" />",
    "UKESM1": "on3/grid-T`: `<field field_ref=\"runoffs\" name=\"friver\" />",
    "UKESM1-3": "on3/grid-T`: `<field field_ref=\"runoffs\" name=\"friver\" />"
  },
  "Variable ocean.friver.tavg-u-hxy-sea.mon.GLB (Omon.friver)": {
    "HadGEM3-GC31": "onm/grid-T`: `<field field_ref=\"runoffs\" name=\"friver\" />",
    "HadGEM3-GC5": "onm/grid-T`: `<field field_ref=\"runoffs\" name=\"friver\" />",
    "UKESM1": "onm/grid-T`: `<field field_ref=\"runoffs\" name=\"friver\" />",
    "UKESM1-3": "onm/grid-T`: `<field field_ref=\"runoffs\" name=\"friver\" />"
  },
  "Variable ocean.hfbasin.tavg-u-hyb-sea.mon.GLB (Omon.hfbasin)": {
    "HadGEM3-GC31": "onm/diaptr`: `<field field_ref=\"sophtadv\" name=\"hfbasin_global\" detect_missing_value=\"true\"> @sophtadv + @sophtldf + @sophteiv </field>` <br> `onm/diaptr`: `<field field_ref=\"sophtadv\" name=\"hfbasin_atlantic\" detect_missing_value=\"true\"> @sophtadv_atl + @sophtldf_atl + @sophteiv_atl </field>` <br> `onm/diaptr`: `<field field_ref=\"sophtadv\" name=\"hfbasin_indopacific\" detect_missing_value=\"true\"> @sophtadv_ipc + @sophtldf_ipc + @sophteiv_ipc </field>",
    "HadGEM3-GC5": "onm/diaptr`: `<field field_ref=\"sophtadv\" name=\"hfbasin\" grid_ref=\"grid_ptr_T_2D\" detect_missing_value=\"true\" > @sophtadv + @sophtldf + @sophteiv </field>",
    "UKESM1": "onm/diaptr`: `<field field_ref=\"sophtadv\" name=\"hfbasin_global\" detect_missing_value=\"true\"> @sophtadv + @sophtldf + @sophteiv </field>` <br> `onm/diaptr`: `<field field_ref=\"sophtadv\" name=\"hfbasin_atlantic\" detect_missing_value=\"true\"> @sophtadv_atl + @sophtldf_atl + @sophteiv_atl </field>` <br> `onm/diaptr`: `<field field_ref=\"sophtadv\" name=\"hfbasin_indopacific\" detect_missing_value=\"true\"> @sophtadv_ipc + @sophtldf_ipc + @sophteiv_ipc </field>",
    "UKESM1-3": "onm/diaptr`: `<field field_ref=\"sophtadv\" name=\"hfbasin_global\" grid_ref=\"grid_ptr_T_2D\" detect_missing_value=\"true\"> @sophtadv + @sophtldf + @sophteiv </field>` <br> `onm/diaptr`: `<field field_ref=\"sophtadv\" name=\"hfbasin_atlantic\" grid_ref=\"grid_ptr_T_2D\" detect_missing_value=\"true\"> @sophtadv_atl + @sophtldf_atl + @sophteiv_atl </field>` <br> `onm/diaptr`: `<field field_ref=\"sophtadv\" name=\"hfbasin_indopacific\" grid_ref=\"grid_ptr_T_2D\" detect_missing_value=\"true\"> @sophtadv_ipc + @sophtldf_ipc + @sophteiv_ipc </field>"
  },
  "Variable ocean.hfbasinpadv.tavg-u-hyb-sea.mon.GLB (Omon.hfbasinpadv)": {
    "HadGEM3-GC31": "onm/diaptr`: `<field field_ref=\"sophteiv\" name=\"hfbasinpadv_global\" />` <br> `onm/diaptr`: `<field field_ref=\"sophteiv_atl\" name=\"hfbasinpadv_atlantic\" />` <br> `onm/diaptr`: `<field field_ref=\"sophteiv_ipc\" name=\"hfbasinpadv_indopacific\" />",
    "HadGEM3-GC5": "onm/diaptr`: `<field field_ref=\"sophteiv\" name=\"hfbasinpadv\" grid_ref=\"grid_ptr_T_2D\" />",
    "UKESM1": "onm/diaptr`: `<field field_ref=\"sophteiv\" name=\"hfbasinpadv_global\" />` <br> `onm/diaptr`: `<field field_ref=\"sophteiv_atl\" name=\"hfbasinpadv_atlantic\" />` <br> `onm/diaptr`: `<field field_ref=\"sophteiv_ipc\" name=\"hfbasinpadv_indopacific\" />",
    "UKESM1-3": "onm/diaptr`: `<field field_ref=\"sophteiv\" name=\"hfbasinpadv_global\" grid_ref=\"grid_ptr_T_2D\" />` <br> `onm/diaptr`: `<field field_ref=\"sophteiv_atl\" name=\"hfbasinpadv_atlantic\" grid_ref=\"grid_ptr_T_2D\" />` <br> `onm/diaptr`: `<field field_ref=\"sophteiv_ipc\" name=\"hfbasinpadv_indopacific\" grid_ref=\"grid_ptr_T_2D\" />"
  },
  "Variable ocean.hfbasinpmadv.tavg-u-hyb-sea.mon.GLB (Omon.hfbasinpmadv)": {
    "HadGEM3-GC31": "onm/diaptr`: `<field field_ref=\"sophteiv\" name=\"hfbasinpadv_global\" />` <br> `onm/diaptr`: `<field field_ref=\"sophteiv_atl\" name=\"hfbasinpadv_atlantic\" />` <br> `onm/diaptr`: `<field field_ref=\"sophteiv_ipc\" name=\"hfbasinpadv_indopacific\" />",
    "HadGEM3-GC5": "onm/diaptr`: `<field field_ref=\"sophteiv\" name=\"hfbasinpadv\" grid_ref=\"grid_ptr_T_2D\" />",
    "UKESM1": "onm/diaptr`: `<field field_ref=\"sophteiv\" name=\"hfbasinpadv_global\" />` <br> `onm/diaptr`: `<field field_ref=\"sophteiv_atl\" name=\"hfbasinpadv_atlantic\" />` <br> `onm/diaptr`: `<field field_ref=\"sophteiv_ipc\" name=\"hfbasinpadv_indopacific\" />",
    "UKESM1-3": "onm/diaptr`: `<field field_ref=\"sophteiv\" name=\"hfbasinpadv_global\" grid_ref=\"grid_ptr_T_2D\" />` <br> `onm/diaptr`: `<field field_ref=\"sophteiv_atl\" name=\"hfbasinpadv_atlantic\" grid_ref=\"grid_ptr_T_2D\" />` <br> `onm/diaptr`: `<field field_ref=\"sophteiv_ipc\" name=\"hfbasinpadv_indopacific\" grid_ref=\"grid_ptr_T_2D\" />"
  },
  "Variable ocean.hfbasinpmdiff.tavg-u-hyb-sea.mon.GLB (Omon.hfbasinpmdiff)": {
    "HadGEM3-GC31": "onm/diaptr`: `<field field_ref=\"sophtldf\" name=\"hfbasinpmdiff_global\" />` <br> `onm/diaptr`: `<field field_ref=\"sophtldf_atl\" name=\"hfbasinpmdiff_atlantic\" />` <br> `onm/diaptr`: `<field field_ref=\"sophtldf_ipc\" name=\"hfbasinpmdiff_indopacific\" />",
    "HadGEM3-GC5": "onm/diaptr`: `<field field_ref=\"sophtldf\" name=\"hfbasinpmdiff\" grid_ref=\"grid_ptr_T_2D\" />",
    "UKESM1": "onm/diaptr`: `<field field_ref=\"sophtldf\" name=\"hfbasinpmdiff_global\" />` <br> `onm/diaptr`: `<field field_ref=\"sophtldf_atl\" name=\"hfbasinpmdiff_atlantic\" />` <br> `onm/diaptr`: `<field field_ref=\"sophtldf_ipc\" name=\"hfbasinpmdiff_indopacific\" />",
    "UKESM1-3": "onm/diaptr`: `<field field_ref=\"sophtldf\" name=\"hfbasinpmdiff_global\" grid_ref=\"grid_ptr_T_2D\" />` <br> `onm/diaptr`: `<field field_ref=\"sophtldf_atl\" name=\"hfbasinpmdiff_atlantic\" grid_ref=\"grid_ptr_T_2D\" />` <br> `onm/diaptr`: `<field field_ref=\"sophtldf_ipc\" name=\"hfbasinpmdiff_indopacific\" grid_ref=\"grid_ptr_T_2D\" />"
  },
  "Variable ocean.hfds.tavg-u-hxy-sea.3hr.GLB (3hr.hfds)": {
    "HadGEM3-GC31": "on3/grid-T`: `<field field_ref=\"qt\" name=\"hfds\" />",
    "HadGEM3-GC5": "on3/grid-T`: `<field field_ref=\"qt\" name=\"hfds\" />",
    "UKESM1": "on3/grid-T`: `<field field_ref=\"qt\" name=\"hfds\" />",
    "UKESM1-3": "on3/grid-T`: `<field field_ref=\"qt\" name=\"hfds\" />"
  },
  "Variable ocean.hfds.tavg-u-hxy-sea.mon.GLB (Omon.hfds)": {
    "HadGEM3-GC31": "onm/grid-T`: `<field field_ref=\"qt\" name=\"hfds\" />",
    "HadGEM3-GC5": "onm/grid-T`: `<field field_ref=\"qt\" name=\"hfds\" />",
    "UKESM1": "onm/grid-T`: `<field field_ref=\"qt\" name=\"hfds\" />",
    "UKESM1-3": "onm/grid-T`: `<field field_ref=\"qt\" name=\"hfds\" />"
  },
  "Variable ocean.hfevapds.tavg-u-hxy-ifs.mon.GLB (Omon.hfevapds)": {
    "HadGEM3-GC31": "onm/grid-T`: `<field field_ref=\"hflx_evap_cea\" name=\"hfevapds\" />",
    "HadGEM3-GC5": "onm/grid-T`: `<field field_ref=\"hflx_evap_cea\" name=\"hfevapds\" />",
    "UKESM1": "onm/grid-T`: `<field field_ref=\"hflx_evap_cea\" name=\"hfevapds\" />",
    "UKESM1-3": "onm/grid-T`: `<field field_ref=\"hflx_evap_cea\" name=\"hfevapds\" />"
  },
  "Variable ocean.hfibthermds.tavg-ol-hxy-sea.mon.GLB (Omon.hfibthermds)": {
    "HadGEM3-GC31": "onm/grid-T`: `<field field_ref=\"berg_total_heat_flux\" />` <br> `onm/grid-T`: `<field field_ref=\"qlatisf3d\" />",
    "HadGEM3-GC5": "onm/grid-T`: `<field field_ref=\"qlatisf3d\" />",
    "UKESM1": "onm/grid-T`: `<field field_ref=\"berg_total_heat_flux\" />` <br> `onm/grid-T`: `<field field_ref=\"qlatisf3d\" />",
    "UKESM1-3": "onm/grid-T`: `<field field_ref=\"berg_total_heat_flux\" />` <br> `onm/grid-T`: `<field field_ref=\"qlatisf3d\" />"
  },
  "Variable ocean.hfrainds.tavg-u-hxy-ifs.mon.GLB (Omon.hfrainds)": {
    "HadGEM3-GC31": "onm/grid-T`: `<field field_ref=\"hflx_rain_cea\" name=\"hfrainds\" />",
    "HadGEM3-GC5": "onm/grid-T`: `<field field_ref=\"hflx_rain_cea\" name=\"hfrainds\" />",
    "UKESM1": "onm/grid-T`: `<field field_ref=\"hflx_rain_cea\" name=\"hfrainds\" />",
    "UKESM1-3": "onm/grid-T`: `<field field_ref=\"hflx_rain_cea\" name=\"hfrainds\" />"
  },
  "Variable ocean.hfrunoffds.tavg-ol-hxy-sea.3hr.GLB (3hr.hfrunoffds)": {
    "HadGEM3-GC31": "on3/grid-T`: `<field field_ref=\"hflx_rnf_cea\" />` <br> `on3/grid-T`: `<field field_ref=\"qhcisf3d\" />",
    "HadGEM3-GC5": "on3/grid-T`: `<field field_ref=\"hflx_rnf_cea\" />` <br> `on3/grid-T`: `<field field_ref=\"qhcisf3d\" />",
    "UKESM1": "on3/grid-T`: `<field field_ref=\"hflx_rnf_cea\" />` <br> `on3/grid-T`: `<field field_ref=\"qhcisf3d\" />",
    "UKESM1-3": "on3/grid-T`: `<field field_ref=\"hflx_rnf_cea\" />` <br> `on3/grid-T`: `<field field_ref=\"qhcisf3d\" />"
  },
  "Variable ocean.hfrunoffds.tavg-ol-hxy-sea.mon.GLB (Omon.hfrunoffds)": {
    "HadGEM3-GC31": "onm/grid-T`: `<field field_ref=\"hflx_rnf_cea\" />` <br> `onm/grid-T`: `<field field_ref=\"qhcisf3d\" />",
    "HadGEM3-GC5": "onm/grid-T`: `<field field_ref=\"hflx_rnf_cea\" />` <br> `onm/grid-T`: `<field field_ref=\"qhcisf3d\" />",
    "UKESM1": "onm/grid-T`: `<field field_ref=\"hflx_rnf_cea\" />` <br> `onm/grid-T`: `<field field_ref=\"qhcisf3d\" />",
    "UKESM1-3": "onm/grid-T`: `<field field_ref=\"hflx_rnf_cea\" />` <br> `onm/grid-T`: `<field field_ref=\"qhcisf3d\" />"
  },
  "Variable ocean.hfsnthermds.tavg-ol-hxy-sea.mon.GLB (Omon.hfsnthermds)": {
    "HadGEM3-GC5": "onm/grid-T`: `<field field_ref=\"hflx_snow_ao_cea\" name=\"hfsnthermds\" />"
  },
  "Variable ocean.hfx.tavg-u-hxy-sea.day.GLB (Oday.hfxint)": {
    "HadGEM3-GC31": "ond/grid-U`: `<field field_ref=\"u_heattr\" name=\"hfxint\" detect_missing_value=\"true\" > @uadv_heattr + @udiff_heattr + @ueiv_heattr </field>",
    "HadGEM3-GC5": "ond/grid-U`: `<field field_ref=\"u_heattr\" name=\"hfxint\" detect_missing_value=\"true\" > @uadv_heattr + @udiff_heattr + @ueiv_heattr </field>",
    "UKESM1": "ond/grid-U`: `<field field_ref=\"u_heattr\" name=\"hfxint\" detect_missing_value=\"true\" > @uadv_heattr + @udiff_heattr + @ueiv_heattr </field>",
    "UKESM1-3": "ond/grid-U`: `<field field_ref=\"u_heattr\" name=\"hfxint\" detect_missing_value=\"true\" > @uadv_heattr + @udiff_heattr + @ueiv_heattr </field>"
  },
  "Variable ocean.hfx.tavg-u-hxy-sea.mon.GLB (Omon.hfxint)": {
    "HadGEM3-GC31": "onm/grid-U`: `<field field_ref=\"u_heattr\" name=\"hfxint\" detect_missing_value=\"true\" > @uadv_heattr + @udiff_heattr + @ueiv_heattr </field>",
    "HadGEM3-GC5": "onm/grid-U`: `<field field_ref=\"u_heattr\" name=\"hfxint\" detect_missing_value=\"true\" > @uadv_heattr + @udiff_heattr + @ueiv_heattr </field>",
    "UKESM1": "onm/grid-U`: `<field field_ref=\"u_heattr\" name=\"hfxint\" detect_missing_value=\"true\" > @uadv_heattr + @udiff_heattr + @ueiv_heattr </field>",
    "UKESM1-3": "onm/grid-U`: `<field field_ref=\"u_heattr\" name=\"hfxint\" detect_missing_value=\"true\" > @uadv_heattr + @udiff_heattr + @ueiv_heattr </field>"
  },
  "Variable ocean.hfy.tavg-u-hxy-sea.day.GLB (Oday.hfyint)": {
    "HadGEM3-GC31": "ond/grid-V`: `<field field_ref=\"v_heattr\" name=\"hfyint\" detect_missing_value=\"true\" > @vadv_heattr + @vdiff_heattr + @veiv_heattr </field>",
    "HadGEM3-GC5": "ond/grid-V`: `<field field_ref=\"v_heattr\" name=\"hfyint\" detect_missing_value=\"true\" > @vadv_heattr + @vdiff_heattr + @veiv_heattr </field>",
    "UKESM1": "ond/grid-V`: `<field field_ref=\"v_heattr\" name=\"hfyint\" detect_missing_value=\"true\" > @vadv_heattr + @vdiff_heattr + @veiv_heattr </field>",
    "UKESM1-3": "ond/grid-V`: `<field field_ref=\"v_heattr\" name=\"hfyint\" detect_missing_value=\"true\" > @vadv_heattr + @vdiff_heattr + @veiv_heattr </field>"
  },
  "Variable ocean.hfy.tavg-u-hxy-sea.mon.GLB (Omon.hfyint)": {
    "HadGEM3-GC31": "onm/grid-V`: `<field field_ref=\"v_heattr\" name=\"hfyint\" detect_missing_value=\"true\" > @vadv_heattr + @vdiff_heattr + @veiv_heattr </field>",
    "HadGEM3-GC5": "onm/grid-V`: `<field field_ref=\"v_heattr\" name=\"hfyint\" detect_missing_value=\"true\" > @vadv_heattr + @vdiff_heattr + @veiv_heattr </field>",
    "UKESM1": "onm/grid-V`: `<field field_ref=\"v_heattr\" name=\"hfyint\" detect_missing_value=\"true\" > @vadv_heattr + @vdiff_heattr + @veiv_heattr </field>",
    "UKESM1-3": "onm/grid-V`: `<field field_ref=\"v_heattr\" name=\"hfyint\" detect_missing_value=\"true\" > @vadv_heattr + @vdiff_heattr + @veiv_heattr </field>"
  },
  "Variable ocean.htovgyre.tavg-u-hyb-sea.mon.GLB (Omon.htovgyre)": {
    "HadGEM3-GC31": "onm/diaptr`: `<field field_ref=\"sophtove\" name=\"htovgyre_global\" > @sophtadv - @sophtove </field>` <br> `onm/diaptr`: `<field field_ref=\"sophtove_atl\" name=\"htovgyre_atlantic\" > @sophtadv_atl - @sophtove_atl </field>` <br> `onm/diaptr`: `<field field_ref=\"sophtove_ipc\" name=\"htovgyre_indopacific\" > @sophtadv_ipc - @sophtove_ipc </field>",
    "HadGEM3-GC5": "onm/diaptr`: `<field field_ref=\"sophtove\" name=\"htovgyre\" grid_ref=\"grid_ptr_T_2D\" > @sophtadv - @sophtove </field>",
    "UKESM1": "onm/diaptr`: `<field field_ref=\"sophtove\" name=\"htovgyre_global\" > @sophtadv - @sophtove </field>` <br> `onm/diaptr`: `<field field_ref=\"sophtove_atl\" name=\"htovgyre_atlantic\" > @sophtadv_atl - @sophtove_atl </field>` <br> `onm/diaptr`: `<field field_ref=\"sophtove_ipc\" name=\"htovgyre_indopacific\" > @sophtadv_ipc - @sophtove_ipc </field>",
    "UKESM1-3": "onm/diaptr`: `<field field_ref=\"sophtove\" name=\"htovgyre_global\" grid_ref=\"grid_ptr_T_2D\" > @sophtadv - @sophtove </field>` <br> `onm/diaptr`: `<field field_ref=\"sophtove_atl\" name=\"htovgyre_atlantic\" grid_ref=\"grid_ptr_T_2D\" > @sophtadv_atl - @sophtove_atl </field>` <br> `onm/diaptr`: `<field field_ref=\"sophtove_ipc\" name=\"htovgyre_indopacific\" grid_ref=\"grid_ptr_T_2D\" > @sophtadv_ipc - @sophtove_ipc </field>"
  },
  "Variable ocean.htovovrt.tavg-u-hyb-sea.mon.GLB (Omon.htovovrt)": {
    "HadGEM3-GC31": "onm/diaptr`: `<field field_ref=\"sophtove\" name=\"htovovrt_global\" />` <br> `onm/diaptr`: `<field field_ref=\"sophtove_atl\" name=\"htovovrt_atlantic\" />` <br> `onm/diaptr`: `<field field_ref=\"sophtove_ipc\" name=\"htovovrt_indopacific\" />",
    "HadGEM3-GC5": "onm/diaptr`: `<field field_ref=\"sophtove\" name=\"htovovrt\" grid_ref=\"grid_ptr_T_2D\" />",
    "UKESM1": "onm/diaptr`: `<field field_ref=\"sophtove\" name=\"htovovrt_global\" />` <br> `onm/diaptr`: `<field field_ref=\"sophtove_atl\" name=\"htovovrt_atlantic\" />` <br> `onm/diaptr`: `<field field_ref=\"sophtove_ipc\" name=\"htovovrt_indopacific\" />",
    "UKESM1-3": "onm/diaptr`: `<field field_ref=\"sophtove\" name=\"htovovrt_global\" grid_ref=\"grid_ptr_T_2D\" />` <br> `onm/diaptr`: `<field field_ref=\"sophtove_atl\" name=\"htovovrt_atlantic\" grid_ref=\"grid_ptr_T_2D\" />` <br> `onm/diaptr`: `<field field_ref=\"sophtove_ipc\" name=\"htovovrt_indopacific\" grid_ref=\"grid_ptr_T_2D\" />"
  },
  "Variable ocean.masscello.tavg-ol-hxy-sea.mon.GLB (Omon.masscello)": {
    "HadGEM3-GC31": "onm/grid-T`: `<field field_ref=\"e3t\" name=\"masscello\" > @e3t * 1026 </field>",
    "HadGEM3-GC5": "onm/grid-T`: `<field field_ref=\"e3t\" name=\"masscello\" > @e3t * 1026 </field>",
    "UKESM1": "onm/grid-T`: `<field field_ref=\"e3t\" name=\"masscello\" > @e3t * 1026 </field>",
    "UKESM1-3": "onm/grid-T`: `<field field_ref=\"e3t\" name=\"masscello\" > @e3t * 1026 </field>"
  },
  "Variable ocean.masso.tavg-u-hm-sea.mon.GLB (Omon.masso)": {
    "HadGEM3-GC31": "onm/scalar`: `<field field_ref=\"voltot\" name=\"masso\" > 1026 * this </field>",
    "HadGEM3-GC5": "onm/scalar`: `<field field_ref=\"voltot\" name=\"masso\" > 1026 * this </field>",
    "UKESM1": "onm/scalar`: `<field field_ref=\"voltot\" name=\"masso\" > 1026 * this </field>",
    "UKESM1-3": "onm/scalar`: `<field field_ref=\"voltot\" name=\"masso\" > 1026 * this </field>"
  },
  "Variable ocean.mlotst.tavg-u-hxy-sea.day.GLB (Eday.mlotst)": {
    "HadGEM3-GC31": "ond/grid-T`: `<field field_ref=\"mldzint_1\" name=\"mlotst\" />",
    "HadGEM3-GC5": "ond/grid-T`: `<field field_ref=\"mldzint_1\" name=\"mlotst\" />",
    "UKESM1": "ond/grid-T`: `<field field_ref=\"mldzint_1\" name=\"mlotst\" />",
    "UKESM1-3": "ond/grid-T`: `<field field_ref=\"mldzint_1\" name=\"mlotst\" />"
  },
  "Variable ocean.mlotst.tavg-u-hxy-sea.mon.GLB (Omon.mlotst)": {
    "HadGEM3-GC31": "onm/grid-T`: `<field field_ref=\"mldzint_1\" name=\"mlotst\" />",
    "HadGEM3-GC5": "onm/grid-T`: `<field field_ref=\"mldzint_1\" name=\"mlotst\" />",
    "UKESM1": "onm/grid-T`: `<field field_ref=\"mldzint_1\" name=\"mlotst\" />",
    "UKESM1-3": "onm/grid-T`: `<field field_ref=\"mldzint_1\" name=\"mlotst\" />"
  },
  "Variable ocean.mlotst.tmax-u-hxy-sea.mon.GLB (Omon.mlotstmax)": {
    "HadGEM3-GC31": "onm/grid-T`: `<field field_ref=\"mldzint_1\" name=\"mlotstmax\" operation=\"maximum\" />",
    "HadGEM3-GC5": "onm/grid-T`: `<field field_ref=\"mldzint_1\" name=\"mlotstmax\" operation=\"maximum\" />",
    "UKESM1": "onm/grid-T`: `<field field_ref=\"mldzint_1\" name=\"mlotstmax\" operation=\"maximum\" />",
    "UKESM1-3": "onm/grid-T`: `<field field_ref=\"mldzint_1\" name=\"mlotstmax\" operation=\"maximum\" />"
  },
  "Variable ocean.mlotst.tmin-u-hxy-sea.mon.GLB (Omon.mlotstmin)": {
    "HadGEM3-GC31": "onm/grid-T`: `<field field_ref=\"mldzint_1\" name=\"mlotstmin\" operation=\"minimum\" />",
    "HadGEM3-GC5": "onm/grid-T`: `<field field_ref=\"mldzint_1\" name=\"mlotstmin\" operation=\"minimum\" />",
    "UKESM1": "onm/grid-T`: `<field field_ref=\"mldzint_1\" name=\"mlotstmin\" operation=\"minimum\" />",
    "UKESM1-3": "onm/grid-T`: `<field field_ref=\"mldzint_1\" name=\"mlotstmin\" operation=\"minimum\" />"
  },
  "Variable ocean.mlotstsq.tavg-u-hxy-sea.mon.GLB (Omon.mlotstsq)": {
    "HadGEM3-GC31": "onm/grid-T`: `<field field_ref=\"mldzint_1\" name=\"mlotstsq\" > this * this </field>",
    "HadGEM3-GC5": "onm/grid-T`: `<field field_ref=\"mldzint_1\" name=\"mlotstsq\" > this * this </field>",
    "UKESM1": "onm/grid-T`: `<field field_ref=\"mldzint_1\" name=\"mlotstsq\" > this * this </field>",
    "UKESM1-3": "onm/grid-T`: `<field field_ref=\"mldzint_1\" name=\"mlotstsq\" > this * this </field>"
  },
  "Variable ocean.msftbarot.tavg-u-hxy-sea.mon.GLB (Omon.msftbarot)": {
    "HadGEM3-GC31": "onm/grid-U`: `<field field_ref=\"u_masstr_vint\" />",
    "HadGEM3-GC5": "onm/grid-U`: `<field field_ref=\"u_masstr_vint\" />",
    "UKESM1": "onm/grid-U`: `<field field_ref=\"u_masstr_vint\" />",
    "UKESM1-3": "onm/grid-U`: `<field field_ref=\"u_masstr_vint\" />"
  },
  "Variable ocean.msfty.tavg-ol-ht-sea.mon.GLB (Omon.msftyz)": {
    "HadGEM3-GC31": "onm/diaptr`: `<field field_ref=\"zomsfglo\" />` <br> `onm/diaptr`: `<field field_ref=\"zomsfatl\" />` <br> `onm/diaptr`: `<field field_ref=\"zomsfipc\" />",
    "HadGEM3-GC5": "onm/diaptr`: `<field field_ref=\"zomsf\" grid_ref=\"grid_ptr_W_3D\" />",
    "UKESM1": "onm/diaptr`: `<field field_ref=\"zomsfglo\" />` <br> `onm/diaptr`: `<field field_ref=\"zomsfatl\" />` <br> `onm/diaptr`: `<field field_ref=\"zomsfipc\" />",
    "UKESM1-3": "onm/diaptr`: `<field field_ref=\"zomsfglo\" grid_ref=\"grid_ptr_W_3D\" />` <br> `onm/diaptr`: `<field field_ref=\"zomsfatl\" grid_ref=\"grid_ptr_W_3D\" />` <br> `onm/diaptr`: `<field field_ref=\"zomsfipc\" grid_ref=\"grid_ptr_W_3D\" />"
  },
  "Variable ocean.msftypa.tavg-ol-ht-sea.mon.GLB (Omon.msftyzmpa)": {
    "HadGEM3-GC31": "onm/diaptr`: `<field field_ref=\"zomsfeivglo\" />` <br> `onm/diaptr`: `<field field_ref=\"zomsfeivatl\" />` <br> `onm/diaptr`: `<field field_ref=\"zomsfeivipc\" />",
    "UKESM1": "onm/diaptr`: `<field field_ref=\"zomsfeivglo\" />` <br> `onm/diaptr`: `<field field_ref=\"zomsfeivatl\" />` <br> `onm/diaptr`: `<field field_ref=\"zomsfeivipc\" />",
    "UKESM1-3": "onm/diaptr`: `<field field_ref=\"zomsfeivglo\" grid_ref=\"grid_ptr_W_3D\" />` <br> `onm/diaptr`: `<field field_ref=\"zomsfeivatl\" grid_ref=\"grid_ptr_W_3D\" />` <br> `onm/diaptr`: `<field field_ref=\"zomsfeivipc\" grid_ref=\"grid_ptr_W_3D\" />"
  },
  "Variable ocean.obvfsq.tavg-ol-hxy-sea.mon.GLB (Omon.obvfsq)": {
    "HadGEM3-GC31": "onm/grid-W`: `<field field_ref=\"bn2\" name=\"obvfsq\" />",
    "HadGEM3-GC5": "onm/grid-W`: `<field field_ref=\"bn2\" name=\"obvfsq\" />",
    "UKESM1": "onm/grid-W`: `<field field_ref=\"bn2\" name=\"obvfsq\" />",
    "UKESM1-3": "onm/grid-W`: `<field field_ref=\"bn2\" name=\"obvfsq\" />"
  },
  "Variable ocean.ocontempdiff.tavg-ol-hxy-sea.yr.GLB (Oyr.ocontempdiff)": {
    "HadGEM3-GC5": "onm/grid-T`: `<field field_ref=\"ttrd_zdfp_li\" name=\"ocontempdiff\" />"
  },
  "Variable ocean.ocontempmint.tavg-u-hxy-sea.yr.GLB (Oyr.ocontempmint)": {
    "HadGEM3-GC5": "onm/grid-T`: `<field field_ref=\"tosmint_con\" name=\"ocontempmint\" />"
  },
  "Variable ocean.ocontemppmdiff.tavg-ol-hxy-sea.yr.GLB (Oyr.ocontemppmdiff)": {
    "HadGEM3-GC5": "onm/grid-T`: `<field field_ref=\"ttrd_iso_li\" name=\"ocontemppmdiff\" />"
  },
  "Variable ocean.ocontemprmadvect.tavg-ol-hxy-sea.yr.GLB (Oyr.ocontemprmadvect)": {
    "HadGEM3-GC5": "onm/grid-T`: `<field field_ref=\"ttrd_totad_li\" name=\"ocontemprmadvect\" />"
  },
  "Variable ocean.ocontemptend.tavg-ol-hxy-sea.yr.GLB (Oyr.ocontemptend)": {
    "HadGEM3-GC5": "onm/grid-T`: `<field field_ref=\"ttrd_tot_li\" name=\"ocontemptend\" />"
  },
  "Variable ocean.opottempdiff.tavg-ol-hxy-sea.yr.GLB (Oyr.opottempdiff)": {
    "HadGEM3-GC31": "onm/grid-T`: `<field field_ref=\"ttrd_zdfp_li\" name=\"opottempdiff\" />",
    "UKESM1": "onm/grid-T`: `<field field_ref=\"ttrd_zdfp_li\" name=\"opottempdiff\" />",
    "UKESM1-3": "onm/grid-T`: `<field field_ref=\"ttrd_zdfp_li\" name=\"opottempdiff\" />"
  },
  "Variable ocean.opottempmint.tavg-u-hxy-sea.yr.GLB (Oyr.opottempmint)": {
    "HadGEM3-GC31": "onm/grid-T`: `<field field_ref=\"tosmint\" name=\"opottempmint\" />",
    "HadGEM3-GC5": "onm/grid-T`: `<field field_ref=\"tosmint_pot\" name=\"opottempmint\" />",
    "UKESM1": "onm/grid-T`: `<field field_ref=\"tosmint\" name=\"opottempmint\" />",
    "UKESM1-3": "onm/grid-T`: `<field field_ref=\"tosmint\" name=\"opottempmint\" />"
  },
  "Variable ocean.opottemppmdiff.tavg-ol-hxy-sea.yr.GLB (Oyr.opottemppmdiff)": {
    "HadGEM3-GC31": "onm/grid-T`: `<field field_ref=\"ttrd_iso_li\" name=\"opottemppmdiff\" />",
    "UKESM1": "onm/grid-T`: `<field field_ref=\"ttrd_iso_li\" name=\"opottemppmdiff\" />",
    "UKESM1-3": "onm/grid-T`: `<field field_ref=\"ttrd_iso_li\" name=\"opottemppmdiff\" />"
  },
  "Variable ocean.opottemprmadvect.tavg-ol-hxy-sea.yr.GLB (Oyr.opottemprmadvect)": {
    "HadGEM3-GC31": "onm/grid-T`: `<field field_ref=\"ttrd_totad_li\" name=\"opottemprmadvect\" />",
    "UKESM1": "onm/grid-T`: `<field field_ref=\"ttrd_totad_li\" name=\"opottemprmadvect\" />",
    "UKESM1-3": "onm/grid-T`: `<field field_ref=\"ttrd_totad_li\" name=\"opottemprmadvect\" />"
  },
  "Variable ocean.opottemptend.tavg-ol-hxy-sea.dec.GLB (Odec.opottemptend)": {
    "HadGEM3-GC31": "onm/grid-T`: `<field field_ref=\"ttrd_tot_li\" name=\"opottemptend\" />",
    "UKESM1": "onm/grid-T`: `<field field_ref=\"ttrd_tot_li\" name=\"opottemptend\" />",
    "UKESM1-3": "onm/grid-T`: `<field field_ref=\"ttrd_tot_li\" name=\"opottemptend\" />"
  },
  "Variable ocean.opottemptend.tavg-ol-hxy-sea.yr.GLB (Oyr.opottemptend)": {
    "HadGEM3-GC31": "onm/grid-T`: `<field field_ref=\"ttrd_tot_li\" name=\"opottemptend\" />",
    "UKESM1": "onm/grid-T`: `<field field_ref=\"ttrd_tot_li\" name=\"opottemptend\" />",
    "UKESM1-3": "onm/grid-T`: `<field field_ref=\"ttrd_tot_li\" name=\"opottemptend\" />"
  },
  "Variable ocean.osaltdiff.tavg-ol-hxy-sea.yr.GLB (Oyr.osaltdiff)": {
    "HadGEM3-GC31": "onm/grid-T`: `<field field_ref=\"strd_zdfp_li\" name=\"osaltdiff\" />",
    "HadGEM3-GC5": "onm/grid-T`: `<field field_ref=\"strd_zdfp_li\" name=\"osaltdiff\" />",
    "UKESM1": "onm/grid-T`: `<field field_ref=\"strd_zdfp_li\" name=\"osaltdiff\" />",
    "UKESM1-3": "onm/grid-T`: `<field field_ref=\"strd_zdfp_li\" name=\"osaltdiff\" />"
  },
  "Variable ocean.osaltpmdiff.tavg-ol-hxy-sea.yr.GLB (Oyr.osaltpmdiff)": {
    "HadGEM3-GC31": "onm/grid-T`: `<field field_ref=\"strd_iso_li\" name=\"osaltpmdiff\" />",
    "HadGEM3-GC5": "onm/grid-T`: `<field field_ref=\"strd_iso_li\" name=\"osaltpmdiff\" />",
    "UKESM1": "onm/grid-T`: `<field field_ref=\"strd_iso_li\" name=\"osaltpmdiff\" />",
    "UKESM1-3": "onm/grid-T`: `<field field_ref=\"strd_iso_li\" name=\"osaltpmdiff\" />"
  },
  "Variable ocean.osaltrmadvect.tavg-ol-hxy-sea.yr.GLB (Oyr.osaltrmadvect)": {
    "HadGEM3-GC31": "onm/grid-T`: `<field field_ref=\"strd_totad_li\" name=\"osaltrmadvect\" />",
    "HadGEM3-GC5": "onm/grid-T`: `<field field_ref=\"strd_totad_li\" name=\"osaltrmadvect\" />",
    "UKESM1": "onm/grid-T`: `<field field_ref=\"strd_totad_li\" name=\"osaltrmadvect\" />",
    "UKESM1-3": "onm/grid-T`: `<field field_ref=\"strd_totad_li\" name=\"osaltrmadvect\" />"
  },
  "Variable ocean.osalttend.tavg-ol-hxy-sea.yr.GLB (Oyr.osalttend)": {
    "HadGEM3-GC31": "onm/grid-T`: `<field field_ref=\"strd_tot_li\" name=\"osalttend\" />",
    "HadGEM3-GC5": "onm/grid-T`: `<field field_ref=\"strd_tot_li\" name=\"osalttend\" />",
    "UKESM1": "onm/grid-T`: `<field field_ref=\"strd_tot_li\" name=\"osalttend\" />",
    "UKESM1-3": "onm/grid-T`: `<field field_ref=\"strd_tot_li\" name=\"osalttend\" />"
  },
  "Variable ocean.pbo.tavg-u-hxy-sea.mon.GLB (Omon.pbo)": {
    "HadGEM3-GC31": "onm/grid-T`: `<field field_ref=\"botpres\" name=\"pbo\" />",
    "HadGEM3-GC5": "onm/grid-T`: `<field field_ref=\"botpres\" name=\"pbo\" />",
    "UKESM1": "onm/grid-T`: `<field field_ref=\"botpres\" name=\"pbo\" />",
    "UKESM1-3": "onm/grid-T`: `<field field_ref=\"botpres\" name=\"pbo\" />"
  },
  "Variable ocean.rsdo.tavg-ol-hxy-sea.day.GLB (Oday.rsdo)": {
    "HadGEM3-GC31": "ond/grid-T`: `<field field_ref=\"qsr3d\" name=\"rsdo\" />",
    "HadGEM3-GC5": "ond/grid-T`: `<field field_ref=\"qsr3d\" name=\"rsdo\" />",
    "UKESM1": "ond/grid-T`: `<field field_ref=\"qsr3d\" name=\"rsdo\" />",
    "UKESM1-3": "ond/grid-T`: `<field field_ref=\"qsr3d\" name=\"rsdo\" />"
  },
  "Variable ocean.rsdoabsorb.tavg-ol-hxy-sea.yr.GLB (Oyr.rsdoabsorb)": {
    "HadGEM3-GC31": "onm/grid-T`: `<field field_ref=\"ttrd_qsr_li\" name=\"rsdoabsorb\" />",
    "HadGEM3-GC5": "onm/grid-T`: `<field field_ref=\"ttrd_qsr_li\" name=\"rsdoabsorb\" />",
    "UKESM1": "onm/grid-T`: `<field field_ref=\"ttrd_qsr_li\" name=\"rsdoabsorb\" />",
    "UKESM1-3": "onm/grid-T`: `<field field_ref=\"ttrd_qsr_li\" name=\"rsdoabsorb\" />"
  },
  "Variable ocean.rsntds.tavg-u-hxy-sea.3hr.GLB (3hr.rsntds)": {
    "HadGEM3-GC31": "on3/grid-T`: `<field field_ref=\"qsr\" name=\"rsntds\" />",
    "HadGEM3-GC5": "on3/grid-T`: `<field field_ref=\"qsr\" name=\"rsntds\" />",
    "UKESM1": "on3/grid-T`: `<field field_ref=\"qsr\" name=\"rsntds\" />",
    "UKESM1-3": "on3/grid-T`: `<field field_ref=\"qsr\" name=\"rsntds\" />"
  },
  "Variable ocean.sfx.tavg-u-hxy-sea.mon.GLB (Omon.sfxint)": {
    "HadGEM3-GC5": "onm/grid-U`: `<field field_ref=\"u_salttr\" name=\"sfxint\" detect_missing_value=\"true\" > @uadv_salttr + @udiff_salttr + @ueiv_salttr </field>"
  },
  "Variable ocean.sfy.tavg-u-hxy-sea.mon.GLB (Omon.sfyint)": {
    "HadGEM3-GC5": "onm/grid-V`: `<field field_ref=\"v_salttr\" name=\"sfyint\" detect_missing_value=\"true\" > @vadv_salttr + @vdiff_salttr + @veiv_salttr </field>"
  },
  "Variable ocean.siflfwbot.tavg-u-hxy-sea.mon.GLB (Omon.fsitherm)": {
    "HadGEM3-GC31": "onm/grid-T`: `<field field_ref=\"fmmflx\" name=\"fsitherm\" />",
    "HadGEM3-GC5": "onm/grid-T`: `<field field_ref=\"fmmflx\" name=\"fsitherm\" />",
    "UKESM1": "onm/grid-T`: `<field field_ref=\"fmmflx\" name=\"fsitherm\" />",
    "UKESM1-3": "onm/grid-T`: `<field field_ref=\"fmmflx\" name=\"fsitherm\" />"
  },
  "Variable ocean.sltbasin.tavg-u-hyb-sea.mon.GLB (Omon.sltbasin)": {
    "HadGEM3-GC31": "onm/diaptr`: `<field field_ref=\"sopstadv\" name=\"sltbasin_global\" detect_missing_value=\"true\"> 1026 * 1000 * (@sopstadv + @sopstldf + @sopsteiv) </field>` <br> `onm/diaptr`: `<field field_ref=\"sopstadv\" name=\"sltbasin_atlantic\" detect_missing_value=\"true\"> 1026 * 1000 * (@sopstadv_atl + @sopstldf_atl + @sopsteiv_atl) </field>` <br> `onm/diaptr`: `<field field_ref=\"sopstadv\" name=\"sltbasin_indopacific\" detect_missing_value=\"true\"> 1026 * 1000 * (@sopstadv_ipc + @sopstldf_ipc + @sopsteiv_ipc) </field>",
    "HadGEM3-GC5": "onm/diaptr`: `<field field_ref=\"sopstadv\" name=\"sltbasin\" grid_ref=\"grid_ptr_T_2D\" detect_missing_value=\"true\" > 1000 * 1000 * (@sopstadv + @sopstldf + @sopsteiv) </field>",
    "UKESM1": "onm/diaptr`: `<field field_ref=\"sopstadv\" name=\"sltbasin_global\" detect_missing_value=\"true\"> 1026 * 1000 * (@sopstadv + @sopstldf + @sopsteiv) </field>` <br> `onm/diaptr`: `<field field_ref=\"sopstadv\" name=\"sltbasin_atlantic\" detect_missing_value=\"true\"> 1026 * 1000 * (@sopstadv_atl + @sopstldf_atl + @sopsteiv_atl) </field>` <br> `onm/diaptr`: `<field field_ref=\"sopstadv\" name=\"sltbasin_indopacific\" detect_missing_value=\"true\"> 1026 * 1000 * (@sopstadv_ipc + @sopstldf_ipc + @sopsteiv_ipc) </field>",
    "UKESM1-3": "onm/diaptr`: `<field field_ref=\"sopstadv\" name=\"sltbasin_global\" grid_ref=\"grid_ptr_T_2D\" detect_missing_value=\"true\"> 1026 * 1000 * (@sopstadv + @sopstldf + @sopsteiv) </field>` <br> `onm/diaptr`: `<field field_ref=\"sopstadv\" name=\"sltbasin_atlantic\" grid_ref=\"grid_ptr_T_2D\" detect_missing_value=\"true\"> 1026 * 1000 * (@sopstadv_atl + @sopstldf_atl + @sopsteiv_atl) </field>` <br> `onm/diaptr`: `<field field_ref=\"sopstadv\" name=\"sltbasin_indopacific\" grid_ref=\"grid_ptr_T_2D\" detect_missing_value=\"true\"> 1026 * 1000 * (@sopstadv_ipc + @sopstldf_ipc + @sopsteiv_ipc) </field>"
  },
  "Variable ocean.sltovgyre.tavg-u-hyb-sea.mon.GLB (Omon.sltovgyre)": {
    "HadGEM3-GC31": "onm/diaptr`: `<field field_ref=\"sopstove\" name=\"sltovgyre_global\" > 1026 * 1000 * (@sopstadv - @sopstove) </field>` <br> `onm/diaptr`: `<field field_ref=\"sopstove\" name=\"sltovgyre_atlantic\" > 1026 * 1000 * (@sopstadv_atl - @sopstove_atl) </field>` <br> `onm/diaptr`: `<field field_ref=\"sopstove\" name=\"sltovgyre_indopacific\" > 1026 * 1000 * (@sopstadv_ipc - @sopstove_ipc) </field>",
    "HadGEM3-GC5": "onm/diaptr`: `<field field_ref=\"sopstove\" name=\"sltovgyre\" grid_ref=\"grid_ptr_T_2D\" > 1000 * 1000 * (@sopstadv - @sopstove) </field>",
    "UKESM1": "onm/diaptr`: `<field field_ref=\"sopstove\" name=\"sltovgyre_global\" > 1026 * 1000 * (@sopstadv - @sopstove) </field>` <br> `onm/diaptr`: `<field field_ref=\"sopstove\" name=\"sltovgyre_atlantic\" > 1026 * 1000 * (@sopstadv_atl - @sopstove_atl) </field>` <br> `onm/diaptr`: `<field field_ref=\"sopstove\" name=\"sltovgyre_indopacific\" > 1026 * 1000 * (@sopstadv_ipc - @sopstove_ipc) </field>",
    "UKESM1-3": "onm/diaptr`: `<field field_ref=\"sopstove\" name=\"sltovgyre_global\" grid_ref=\"grid_ptr_T_2D\" > 1026 * 1000 * (@sopstadv - @sopstove) </field>` <br> `onm/diaptr`: `<field field_ref=\"sopstove\" name=\"sltovgyre_atlantic\" grid_ref=\"grid_ptr_T_2D\" > 1026 * 1000 * (@sopstadv_atl - @sopstove_atl) </field>` <br> `onm/diaptr`: `<field field_ref=\"sopstove\" name=\"sltovgyre_indopacific\" grid_ref=\"grid_ptr_T_2D\" > 1026 * 1000 * (@sopstadv_ipc - @sopstove_ipc) </field>"
  },
  "Variable ocean.sltovovrt.tavg-u-hyb-sea.mon.GLB (Omon.sltovovrt)": {
    "HadGEM3-GC31": "onm/diaptr`: `<field field_ref=\"sopstove\" name=\"sltovovrt_global\" > 1026 * 1000 * @sopstove </field>` <br> `onm/diaptr`: `<field field_ref=\"sopstove\" name=\"sltovovrt_atlantic\" > 1026 * 1000 * @sopstove_atl </field>` <br> `onm/diaptr`: `<field field_ref=\"sopstove\" name=\"sltovovrt_indopacific\" > 1026 * 1000 * @sopstove_ipc </field>",
    "HadGEM3-GC5": "onm/diaptr`: `<field field_ref=\"sopstove\" name=\"sltovovrt\" grid_ref=\"grid_ptr_T_2D\" > 1000 * 1000 * @sopstove </field>",
    "UKESM1": "onm/diaptr`: `<field field_ref=\"sopstove\" name=\"sltovovrt_global\" > 1026 * 1000 * @sopstove </field>` <br> `onm/diaptr`: `<field field_ref=\"sopstove\" name=\"sltovovrt_atlantic\" > 1026 * 1000 * @sopstove_atl </field>` <br> `onm/diaptr`: `<field field_ref=\"sopstove\" name=\"sltovovrt_indopacific\" > 1026 * 1000 * @sopstove_ipc </field>",
    "UKESM1-3": "onm/diaptr`: `<field field_ref=\"sopstove\" name=\"sltovovrt_global\" grid_ref=\"grid_ptr_T_2D\" > 1026 * 1000 * @sopstove </field>` <br> `onm/diaptr`: `<field field_ref=\"sopstove\" name=\"sltovovrt_atlantic\" grid_ref=\"grid_ptr_T_2D\" > 1026 * 1000 * @sopstove_atl </field>` <br> `onm/diaptr`: `<field field_ref=\"sopstove\" name=\"sltovovrt_indopacific\" grid_ref=\"grid_ptr_T_2D\" > 1026 * 1000 * @sopstove_ipc </field>"
  },
  "Variable ocean.so.tavg-ol-hm-sea.mon.GLB (Omon.soga)": {
    "HadGEM3-GC31": "onm/grid-T`: `<field field_ref=\"soce\" name=\"so\" operation=\"average\" freq_op=\"1mo\" > @soce_e3t / @e3t </field>` <br> `onm/grid-T`: `<field field_ref=\"e3t\" name=\"thkcello\" />",
    "HadGEM3-GC5": "onm/grid-T`: `<field field_ref=\"soce_abs\" name=\"so\" operation=\"average\" freq_op=\"1mo\" > @soce_abs_e3t / @e3t </field>` <br> `onm/grid-T`: `<field field_ref=\"e3t\" name=\"thkcello\" />",
    "UKESM1": "onm/grid-T`: `<field field_ref=\"soce\" name=\"so\" operation=\"average\" freq_op=\"1mo\" > @soce_e3t / @e3t </field>` <br> `onm/grid-T`: `<field field_ref=\"e3t\" name=\"thkcello\" />",
    "UKESM1-3": "onm/grid-T`: `<field field_ref=\"soce\" name=\"so\" operation=\"average\" freq_op=\"1mo\" > @soce_e3t / @e3t </field>` <br> `onm/grid-T`: `<field field_ref=\"e3t\" name=\"thkcello\" />"
  },
  "Variable ocean.so.tavg-ol-hxy-sea.day.GLB (Oday.so)": {
    "HadGEM3-GC31": "ond/grid-T`: `<field field_ref=\"soce\" name=\"so\" operation=\"average\" freq_op=\"1d\" > @soce_e3t / @e3t </field>",
    "HadGEM3-GC5": "ond/grid-T`: `<field field_ref=\"soce_abs\" name=\"so\" operation=\"average\" freq_op=\"1d\" > @soce_abs_e3t / @e3t </field>",
    "UKESM1": "ond/grid-T`: `<field field_ref=\"soce\" name=\"so\" operation=\"average\" freq_op=\"1d\" > @soce_e3t / @e3t </field>",
    "UKESM1-3": "ond/grid-T`: `<field field_ref=\"soce\" name=\"so\" operation=\"average\" freq_op=\"1d\" > @soce_e3t / @e3t </field>"
  },
  "Variable ocean.so.tavg-ol-hxy-sea.mon.GLB (Omon.so)": {
    "HadGEM3-GC31": "onm/grid-T`: `<field field_ref=\"soce\" name=\"so\" operation=\"average\" freq_op=\"1mo\" > @soce_e3t / @e3t </field>",
    "HadGEM3-GC5": "onm/grid-T`: `<field field_ref=\"soce_abs\" name=\"so\" operation=\"average\" freq_op=\"1mo\" > @soce_abs_e3t / @e3t </field>",
    "UKESM1": "onm/grid-T`: `<field field_ref=\"soce\" name=\"so\" operation=\"average\" freq_op=\"1mo\" > @soce_e3t / @e3t </field>",
    "UKESM1-3": "onm/grid-T`: `<field field_ref=\"soce\" name=\"so\" operation=\"average\" freq_op=\"1mo\" > @soce_e3t / @e3t </field>"
  },
  "Variable ocean.sob.tavg-u-hxy-sea.mon.GLB (Omon.sob)": {
    "HadGEM3-GC31": "onm/grid-T`: `<field field_ref=\"sbs\" name=\"sob\" />",
    "HadGEM3-GC5": "onm/grid-T`: `<field field_ref=\"sbs_abs\" name=\"sob\" />",
    "UKESM1": "onm/grid-T`: `<field field_ref=\"sbs\" name=\"sob\" />",
    "UKESM1-3": "onm/grid-T`: `<field field_ref=\"sbs\" name=\"sob\" />"
  },
  "Variable ocean.somint.tavg-u-hxy-sea.yr.GLB (Oyr.somint)": {
    "HadGEM3-GC31": "onm/grid-T`: `<field field_ref=\"somint\" />",
    "HadGEM3-GC5": "onm/grid-T`: `<field field_ref=\"somint_abs\" name=\"somint\" />",
    "UKESM1": "onm/grid-T`: `<field field_ref=\"somint\" />",
    "UKESM1-3": "onm/grid-T`: `<field field_ref=\"somint\" />"
  },
  "Variable ocean.sos.tavg-u-hm-sea.mon.GLB (Omon.sosga)": {
    "HadGEM3-GC31": "onm/grid-T`: `<field field_ref=\"sss\" name=\"sos\" />` <br> `onm/grid-T`: `<field field_ref=\"e3t\" name=\"thkcello\" />",
    "HadGEM3-GC5": "onm/grid-T`: `<field field_ref=\"sss_abs\" name=\"sos\" />` <br> `onm/grid-T`: `<field field_ref=\"e3t\" name=\"thkcello\" />",
    "UKESM1": "onm/grid-T`: `<field field_ref=\"sss\" name=\"sos\" />` <br> `onm/grid-T`: `<field field_ref=\"e3t\" name=\"thkcello\" />",
    "UKESM1-3": "onm/grid-T`: `<field field_ref=\"sss\" name=\"sos\" />` <br> `onm/grid-T`: `<field field_ref=\"e3t\" name=\"thkcello\" />"
  },
  "Variable ocean.sos.tavg-u-hxy-sea.day.GLB (Oday.sos)": {
    "HadGEM3-GC31": "ond/grid-T`: `<field field_ref=\"sss\" name=\"sos\" />",
    "HadGEM3-GC5": "ond/grid-T`: `<field field_ref=\"sss_abs\" name=\"sos\" />",
    "UKESM1": "ond/grid-T`: `<field field_ref=\"sss\" name=\"sos\" />",
    "UKESM1-3": "ond/grid-T`: `<field field_ref=\"sss\" name=\"sos\" />"
  },
  "Variable ocean.sos.tavg-u-hxy-sea.mon.GLB (Omon.sos)": {
    "HadGEM3-GC31": "onm/grid-T`: `<field field_ref=\"sss\" name=\"sos\" />",
    "HadGEM3-GC5": "onm/grid-T`: `<field field_ref=\"sss_abs\" name=\"sos\" />",
    "UKESM1": "onm/grid-T`: `<field field_ref=\"sss\" name=\"sos\" />",
    "UKESM1-3": "onm/grid-T`: `<field field_ref=\"sss\" name=\"sos\" />"
  },
  "Variable ocean.sossq.tavg-u-hxy-sea.mon.GLB (Omon.sossq)": {
    "HadGEM3-GC31": "onm/grid-T`: `<field field_ref=\"sss2\" name=\"sossq\" />",
    "HadGEM3-GC5": "onm/grid-T`: `<field field_ref=\"sss2_abs\" name=\"sossq\" />",
    "UKESM1": "onm/grid-T`: `<field field_ref=\"sss2\" name=\"sossq\" />",
    "UKESM1-3": "onm/grid-T`: `<field field_ref=\"sss2\" name=\"sossq\" />"
  },
  "Variable ocean.t20d.tavg-u-hxy-sea.day.GLB (Eday.t20d)": {
    "HadGEM3-GC31": "ond/grid-T`: `<field field_ref=\"20d\" name=\"t20d\" />",
    "HadGEM3-GC5": "ond/grid-T`: `<field field_ref=\"20d\" name=\"t20d\" />",
    "UKESM1": "ond/grid-T`: `<field field_ref=\"20d\" name=\"t20d\" />",
    "UKESM1-3": "ond/grid-T`: `<field field_ref=\"20d\" name=\"t20d\" />"
  },
  "Variable ocean.t20d.tavg-u-hxy-sea.mon.GLB (Emon.t20d)": {
    "HadGEM3-GC31": "onm/grid-T`: `<field field_ref=\"20d\" name=\"t20d\" />",
    "HadGEM3-GC5": "onm/grid-T`: `<field field_ref=\"20d\" name=\"t20d\" />",
    "UKESM1": "onm/grid-T`: `<field field_ref=\"20d\" name=\"t20d\" />",
    "UKESM1-3": "onm/grid-T`: `<field field_ref=\"20d\" name=\"t20d\" />"
  },
  "Variable ocean.tauuo.tavg-u-hxy-sea.3hr.GLB (3hr.tauuo)": {
    "HadGEM3-GC31": "on3/grid-U`: `<field field_ref=\"utau\" name=\"tauuo\" />",
    "HadGEM3-GC5": "on3/grid-U`: `<field field_ref=\"utau\" name=\"tauuo\" />",
    "UKESM1": "on3/grid-U`: `<field field_ref=\"utau\" name=\"tauuo\" />",
    "UKESM1-3": "on3/grid-U`: `<field field_ref=\"utau\" name=\"tauuo\" />"
  },
  "Variable ocean.tauuo.tavg-u-hxy-sea.mon.GLB (Omon.tauuo)": {
    "HadGEM3-GC31": "onm/grid-U`: `<field field_ref=\"utau\" name=\"tauuo\" />",
    "HadGEM3-GC5": "onm/grid-U`: `<field field_ref=\"utau\" name=\"tauuo\" />",
    "UKESM1": "onm/grid-U`: `<field field_ref=\"utau\" name=\"tauuo\" />",
    "UKESM1-3": "onm/grid-U`: `<field field_ref=\"utau\" name=\"tauuo\" />"
  },
  "Variable ocean.tauvo.tavg-u-hxy-sea.3hr.GLB (3hr.tauvo)": {
    "HadGEM3-GC31": "on3/grid-V`: `<field field_ref=\"vtau\" name=\"tauvo\" />",
    "HadGEM3-GC5": "on3/grid-V`: `<field field_ref=\"vtau\" name=\"tauvo\" />",
    "UKESM1": "on3/grid-V`: `<field field_ref=\"vtau\" name=\"tauvo\" />",
    "UKESM1-3": "on3/grid-V`: `<field field_ref=\"vtau\" name=\"tauvo\" />"
  },
  "Variable ocean.tauvo.tavg-u-hxy-sea.mon.GLB (Omon.tauvo)": {
    "HadGEM3-GC31": "onm/grid-V`: `<field field_ref=\"vtau\" name=\"tauvo\" />",
    "HadGEM3-GC5": "onm/grid-V`: `<field field_ref=\"vtau\" name=\"tauvo\" />",
    "UKESM1": "onm/grid-V`: `<field field_ref=\"vtau\" name=\"tauvo\" />",
    "UKESM1-3": "onm/grid-V`: `<field field_ref=\"vtau\" name=\"tauvo\" />"
  },
  "Variable ocean.thetao.tavg-d2000m-hxy-sea.mon.GLB (Emon.thetaot2000)": {
    "HadGEM3-GC31": "onm/grid-T`: `<field field_ref=\"toce\" name=\"thetao\" operation=\"average\" freq_op=\"1mo\" > @toce_e3t / @e3t </field>` <br> `onm/grid-T`: `<field field_ref=\"e3t\" name=\"thkcello\" />",
    "HadGEM3-GC5": "onm/grid-T`: `<field field_ref=\"toce_pot\" name=\"thetao\" operation=\"average\" freq_op=\"1mo\" > @toce_pot_e3t / @e3t </field>` <br> `onm/grid-T`: `<field field_ref=\"e3t\" name=\"thkcello\" />",
    "UKESM1": "onm/grid-T`: `<field field_ref=\"toce\" name=\"thetao\" operation=\"average\" freq_op=\"1mo\" > @toce_e3t / @e3t </field>` <br> `onm/grid-T`: `<field field_ref=\"e3t\" name=\"thkcello\" />",
    "UKESM1-3": "onm/grid-T`: `<field field_ref=\"toce\" name=\"thetao\" operation=\"average\" freq_op=\"1mo\" > @toce_e3t / @e3t </field>` <br> `onm/grid-T`: `<field field_ref=\"e3t\" name=\"thkcello\" />"
  },
  "Variable ocean.thetao.tavg-d300m-hxy-sea.mon.GLB (Emon.thetaot300)": {
    "HadGEM3-GC31": "onm/grid-T`: `<field field_ref=\"toce\" name=\"thetao\" operation=\"average\" freq_op=\"1mo\" > @toce_e3t / @e3t </field>` <br> `onm/grid-T`: `<field field_ref=\"e3t\" name=\"thkcello\" />",
    "HadGEM3-GC5": "onm/grid-T`: `<field field_ref=\"toce_pot\" name=\"thetao\" operation=\"average\" freq_op=\"1mo\" > @toce_pot_e3t / @e3t </field>` <br> `onm/grid-T`: `<field field_ref=\"e3t\" name=\"thkcello\" />",
    "UKESM1": "onm/grid-T`: `<field field_ref=\"toce\" name=\"thetao\" operation=\"average\" freq_op=\"1mo\" > @toce_e3t / @e3t </field>` <br> `onm/grid-T`: `<field field_ref=\"e3t\" name=\"thkcello\" />",
    "UKESM1-3": "onm/grid-T`: `<field field_ref=\"toce\" name=\"thetao\" operation=\"average\" freq_op=\"1mo\" > @toce_e3t / @e3t </field>` <br> `onm/grid-T`: `<field field_ref=\"e3t\" name=\"thkcello\" />"
  },
  "Variable ocean.thetao.tavg-d700m-hxy-sea.mon.GLB (Emon.thetaot700)": {
    "HadGEM3-GC31": "onm/grid-T`: `<field field_ref=\"toce\" name=\"thetao\" operation=\"average\" freq_op=\"1mo\" > @toce_e3t / @e3t </field>` <br> `onm/grid-T`: `<field field_ref=\"e3t\" name=\"thkcello\" />",
    "HadGEM3-GC5": "onm/grid-T`: `<field field_ref=\"toce_pot\" name=\"thetao\" operation=\"average\" freq_op=\"1mo\" > @toce_pot_e3t / @e3t </field>` <br> `onm/grid-T`: `<field field_ref=\"e3t\" name=\"thkcello\" />",
    "UKESM1": "onm/grid-T`: `<field field_ref=\"toce\" name=\"thetao\" operation=\"average\" freq_op=\"1mo\" > @toce_e3t / @e3t </field>` <br> `onm/grid-T`: `<field field_ref=\"e3t\" name=\"thkcello\" />",
    "UKESM1-3": "onm/grid-T`: `<field field_ref=\"toce\" name=\"thetao\" operation=\"average\" freq_op=\"1mo\" > @toce_e3t / @e3t </field>` <br> `onm/grid-T`: `<field field_ref=\"e3t\" name=\"thkcello\" />"
  },
  "Variable ocean.thetao.tavg-ol-hm-sea.mon.GLB (Omon.thetaoga)": {
    "HadGEM3-GC31": "onm/grid-T`: `<field field_ref=\"toce\" name=\"thetao\" operation=\"average\" freq_op=\"1mo\" > @toce_e3t / @e3t </field>` <br> `onm/grid-T`: `<field field_ref=\"e3t\" name=\"thkcello\" />",
    "HadGEM3-GC5": "onm/grid-T`: `<field field_ref=\"toce_pot\" name=\"thetao\" operation=\"average\" freq_op=\"1mo\" > @toce_pot_e3t / @e3t </field>` <br> `onm/grid-T`: `<field field_ref=\"e3t\" name=\"thkcello\" />",
    "UKESM1": "onm/grid-T`: `<field field_ref=\"toce\" name=\"thetao\" operation=\"average\" freq_op=\"1mo\" > @toce_e3t / @e3t </field>` <br> `onm/grid-T`: `<field field_ref=\"e3t\" name=\"thkcello\" />",
    "UKESM1-3": "onm/grid-T`: `<field field_ref=\"toce\" name=\"thetao\" operation=\"average\" freq_op=\"1mo\" > @toce_e3t / @e3t </field>` <br> `onm/grid-T`: `<field field_ref=\"e3t\" name=\"thkcello\" />"
  },
  "Variable ocean.thetao.tavg-ol-hxy-sea.mon.GLB (Omon.thetao)": {
    "HadGEM3-GC31": "onm/grid-T`: `<field field_ref=\"toce\" name=\"thetao\" operation=\"average\" freq_op=\"1mo\" > @toce_e3t / @e3t </field>",
    "HadGEM3-GC5": "onm/grid-T`: `<field field_ref=\"toce_pot\" name=\"thetao\" operation=\"average\" freq_op=\"1mo\" > @toce_pot_e3t / @e3t </field>",
    "UKESM1": "onm/grid-T`: `<field field_ref=\"toce\" name=\"thetao\" operation=\"average\" freq_op=\"1mo\" > @toce_e3t / @e3t </field>",
    "UKESM1-3": "onm/grid-T`: `<field field_ref=\"toce\" name=\"thetao\" operation=\"average\" freq_op=\"1mo\" > @toce_e3t / @e3t </field>"
  },
  "Variable ocean.thetao.tavg-op20bar-hxy-sea.day.GLB (Oday.thetao200)": {
    "HadGEM3-GC31": "ond/grid-T`: `<field field_ref=\"toce\" name=\"thetao\" operation=\"average\" freq_op=\"1d\" > @toce_e3t / @e3t </field>",
    "HadGEM3-GC5": "ond/grid-T`: `<field field_ref=\"toce_pot\" name=\"thetao\" operation=\"average\" freq_op=\"1d\" > @toce_pot_e3t / @e3t </field>",
    "UKESM1": "ond/grid-T`: `<field field_ref=\"toce\" name=\"thetao\" operation=\"average\" freq_op=\"1d\" > @toce_e3t / @e3t </field>",
    "UKESM1-3": "ond/grid-T`: `<field field_ref=\"toce\" name=\"thetao\" operation=\"average\" freq_op=\"1d\" > @toce_e3t / @e3t </field>"
  },
  "Variable ocean.thetaot.tavg-u-hxy-sea.mon.GLB (Emon.thetaot)": {
    "HadGEM3-GC31": "onm/grid-T`: `<field field_ref=\"toce\" name=\"thetao\" operation=\"average\" freq_op=\"1mo\" > @toce_e3t / @e3t </field>` <br> `onm/grid-T`: `<field field_ref=\"e3t\" name=\"thkcello\" />",
    "HadGEM3-GC5": "onm/grid-T`: `<field field_ref=\"toce_pot\" name=\"thetao\" operation=\"average\" freq_op=\"1mo\" > @toce_pot_e3t / @e3t </field>` <br> `onm/grid-T`: `<field field_ref=\"e3t\" name=\"thkcello\" />",
    "UKESM1": "onm/grid-T`: `<field field_ref=\"toce\" name=\"thetao\" operation=\"average\" freq_op=\"1mo\" > @toce_e3t / @e3t </field>` <br> `onm/grid-T`: `<field field_ref=\"e3t\" name=\"thkcello\" />",
    "UKESM1-3": "onm/grid-T`: `<field field_ref=\"toce\" name=\"thetao\" operation=\"average\" freq_op=\"1mo\" > @toce_e3t / @e3t </field>` <br> `onm/grid-T`: `<field field_ref=\"e3t\" name=\"thkcello\" />"
  },
  "Variable ocean.thkcello.tavg-ol-hxy-sea.mon.GLB (Omon.thkcello)": {
    "HadGEM3-GC31": "onm/grid-T`: `<field field_ref=\"e3t\" name=\"thkcello\" />",
    "HadGEM3-GC5": "onm/grid-T`: `<field field_ref=\"e3t\" name=\"thkcello\" />",
    "UKESM1": "onm/grid-T`: `<field field_ref=\"e3t\" name=\"thkcello\" />",
    "UKESM1-3": "onm/grid-T`: `<field field_ref=\"e3t\" name=\"thkcello\" />"
  },
  "Variable ocean.thkcelluo.tavg-ol-hxy-sea.mon.GLB (Omon.thkcelluo)": {
    "HadGEM3-GC31": "onm/grid-U`: `<field field_ref=\"e3u\" name=\"thkcelluo\" />",
    "HadGEM3-GC5": "onm/grid-U`: `<field field_ref=\"e3u\" name=\"thkcelluo\" />",
    "UKESM1": "onm/grid-U`: `<field field_ref=\"e3u\" name=\"thkcelluo\" />",
    "UKESM1-3": "onm/grid-U`: `<field field_ref=\"e3u\" name=\"thkcelluo\" />"
  },
  "Variable ocean.thkcellvo.tavg-ol-hxy-sea.mon.GLB (Omon.thkcellvo)": {
    "HadGEM3-GC31": "onm/grid-V`: `<field field_ref=\"e3v\" name=\"thkcellvo\" />",
    "HadGEM3-GC5": "onm/grid-V`: `<field field_ref=\"e3v\" name=\"thkcellvo\" />",
    "UKESM1": "onm/grid-V`: `<field field_ref=\"e3v\" name=\"thkcellvo\" />",
    "UKESM1-3": "onm/grid-V`: `<field field_ref=\"e3v\" name=\"thkcellvo\" />"
  },
  "Variable ocean.tnkebto.tavg-u-hxy-sea.yr.GLB (Oyr.tnkebto)": {
    "HadGEM3-GC31": "onm/grid-T`: `<field field_ref=\"ketrd_eiv\" name=\"tnkebto\" />",
    "UKESM1": "onm/grid-T`: `<field field_ref=\"ketrd_eiv\" name=\"tnkebto\" />",
    "UKESM1-3": "onm/grid-T`: `<field field_ref=\"ketrd_eiv\" name=\"tnkebto\" />"
  },
  "Variable ocean.tnpeo.tavg-u-hxy-sea.yr.GLB (Oyr.tnpeo)": {
    "HadGEM3-GC31": "onm/grid-T`: `<field field_ref=\"tnpeo\" />",
    "HadGEM3-GC5": "onm/grid-T`: `<field field_ref=\"tnpeo\" />",
    "UKESM1": "onm/grid-T`: `<field field_ref=\"tnpeo\" />",
    "UKESM1-3": "onm/grid-T`: `<field field_ref=\"tnpeo\" />"
  },
  "Variable ocean.tob.tavg-u-hxy-sea.mon.GLB (Omon.tob)": {
    "HadGEM3-GC31": "onm/grid-T`: `<field field_ref=\"sbt\" name=\"tob\" />",
    "UKESM1": "onm/grid-T`: `<field field_ref=\"sbt\" name=\"tob\" />",
    "UKESM1-3": "onm/grid-T`: `<field field_ref=\"sbt\" name=\"tob\" />"
  },
  "Variable ocean.tos.tavg-u-hm-sea.mon.GLB (Omon.tosga)": {
    "HadGEM3-GC31": "onm/grid-T`: `<field field_ref=\"sst\" name=\"tos\" />` <br> `onm/grid-T`: `<field field_ref=\"e3t\" name=\"thkcello\" />",
    "HadGEM3-GC5": "onm/grid-T`: `<field field_ref=\"sst_pot\" name=\"tos\" />` <br> `onm/grid-T`: `<field field_ref=\"e3t\" name=\"thkcello\" />",
    "UKESM1": "onm/grid-T`: `<field field_ref=\"sst\" name=\"tos\" />` <br> `onm/grid-T`: `<field field_ref=\"e3t\" name=\"thkcello\" />",
    "UKESM1-3": "onm/grid-T`: `<field field_ref=\"sst\" name=\"tos\" />` <br> `onm/grid-T`: `<field field_ref=\"e3t\" name=\"thkcello\" />"
  },
  "Variable ocean.tos.tavg-u-hxy-sea.day.GLB (Oday.tos)": {
    "HadGEM3-GC31": "ond/grid-T`: `<field field_ref=\"sst\" name=\"tos\" />",
    "HadGEM3-GC5": "ond/grid-T`: `<field field_ref=\"sst_pot\" name=\"tos\" />",
    "UKESM1": "ond/grid-T`: `<field field_ref=\"sst\" name=\"tos\" />",
    "UKESM1-3": "ond/grid-T`: `<field field_ref=\"sst\" name=\"tos\" />"
  },
  "Variable ocean.tos.tavg-u-hxy-sea.mon.GLB (Omon.tos)": {
    "HadGEM3-GC31": "onm/grid-T`: `<field field_ref=\"sst\" name=\"tos\" />",
    "HadGEM3-GC5": "onm/grid-T`: `<field field_ref=\"sst_pot\" name=\"tos\" />",
    "UKESM1": "onm/grid-T`: `<field field_ref=\"sst\" name=\"tos\" />",
    "UKESM1-3": "onm/grid-T`: `<field field_ref=\"sst\" name=\"tos\" />"
  },
  "Variable ocean.tos.tpt-u-hxy-sea.3hr.GLB (3hr.tos)": {
    "HadGEM3-GC31": "on3/grid-T`: `<field field_ref=\"sst\" operation=\"instant\" name=\"tos\" />",
    "HadGEM3-GC5": "on3/grid-T`: `<field field_ref=\"sst_m_pot\" operation=\"instant\" name=\"tos\" />",
    "UKESM1": "on3/grid-T`: `<field field_ref=\"sst\" operation=\"instant\" name=\"tos\" />",
    "UKESM1-3": "on3/grid-T`: `<field field_ref=\"sst\" operation=\"instant\" name=\"tos\" />"
  },
  "Variable ocean.tossq.tavg-u-hxy-sea.day.GLB (Oday.tossq)": {
    "HadGEM3-GC31": "ond/grid-T`: `<field field_ref=\"sst2\" name=\"tossq\" />",
    "HadGEM3-GC5": "ond/grid-T`: `<field field_ref=\"sst_pot\" name=\"tossq\" > this * this </field>",
    "UKESM1": "ond/grid-T`: `<field field_ref=\"sst2\" name=\"tossq\" />",
    "UKESM1-3": "ond/grid-T`: `<field field_ref=\"sst2\" name=\"tossq\" />"
  },
  "Variable ocean.tossq.tavg-u-hxy-sea.mon.GLB (Omon.tossq)": {
    "HadGEM3-GC31": "onm/grid-T`: `<field field_ref=\"sst2\" name=\"tossq\" />",
    "HadGEM3-GC5": "onm/grid-T`: `<field field_ref=\"sst_m_pot\" name=\"tossq\" > this * this </field>",
    "UKESM1": "onm/grid-T`: `<field field_ref=\"sst2\" name=\"tossq\" />",
    "UKESM1-3": "onm/grid-T`: `<field field_ref=\"sst2\" name=\"tossq\" />"
  },
  "Variable ocean.umo.tavg-ol-hxy-sea.mon.GLB (Omon.umo)": {
    "HadGEM3-GC31": "onm/grid-U`: `<field field_ref=\"u_masstr\" name=\"umo\" detect_missing_value=\"true\"> @u_masstr + @ueiv_masstr </field>",
    "HadGEM3-GC5": "onm/grid-U`: `<field field_ref=\"u_masstr\" name=\"umo\" detect_missing_value=\"true\"> @u_masstr + @ueiv_masstr </field>",
    "UKESM1": "onm/grid-U`: `<field field_ref=\"u_masstr\" name=\"umo\" detect_missing_value=\"true\"> @u_masstr + @ueiv_masstr </field>",
    "UKESM1-3": "onm/grid-U`: `<field field_ref=\"u_masstr\" name=\"umo\" detect_missing_value=\"true\"> @u_masstr + @ueiv_masstr </field>"
  },
  "Variable ocean.uo.tavg-ol-hxy-sea.mon.GLB (Omon.uo)": {
    "HadGEM3-GC31": "onm/grid-U`: `<field field_ref=\"uoce\" name=\"uo\" operation=\"average\" freq_op=\"1mo\" > @uoce_e3u / @e3u </field>",
    "HadGEM3-GC5": "onm/grid-U`: `<field field_ref=\"uoce\" name=\"uo\" operation=\"average\" freq_op=\"1mo\" > @uoce_e3u / @e3u </field>",
    "UKESM1": "onm/grid-U`: `<field field_ref=\"uoce\" name=\"uo\" operation=\"average\" freq_op=\"1mo\" > @uoce_e3u / @e3u </field>",
    "UKESM1-3": "onm/grid-U`: `<field field_ref=\"uoce\" name=\"uo\" operation=\"average\" freq_op=\"1mo\" > @uoce_e3u / @e3u </field>"
  },
  "Variable ocean.uos.tavg-u-hxy-sea.day.GLB (Oday.uos)": {
    "HadGEM3-GC31": "ond/grid-U`: `<field field_ref=\"ssu\" name=\"uos\" />",
    "HadGEM3-GC5": "ond/grid-U`: `<field field_ref=\"ssu\" name=\"uos\" />",
    "UKESM1": "ond/grid-U`: `<field field_ref=\"ssu\" name=\"uos\" />",
    "UKESM1-3": "ond/grid-U`: `<field field_ref=\"ssu\" name=\"uos\" />"
  },
  "Variable ocean.vmo.tavg-ol-hxy-sea.mon.GLB (Omon.vmo)": {
    "HadGEM3-GC31": "onm/grid-V`: `<field field_ref=\"v_masstr\" name=\"vmo\" detect_missing_value=\"true\"> @v_masstr + @veiv_masstr </field>",
    "HadGEM3-GC5": "onm/grid-V`: `<field field_ref=\"v_masstr\" name=\"vmo\" detect_missing_value=\"true\"> @v_masstr + @veiv_masstr </field>",
    "UKESM1": "onm/grid-V`: `<field field_ref=\"v_masstr\" name=\"vmo\" detect_missing_value=\"true\"> @v_masstr + @veiv_masstr </field>",
    "UKESM1-3": "onm/grid-V`: `<field field_ref=\"v_masstr\" name=\"vmo\" detect_missing_value=\"true\"> @v_masstr + @veiv_masstr </field>"
  },
  "Variable ocean.vo.tavg-ol-hxy-sea.mon.GLB (Omon.vo)": {
    "HadGEM3-GC31": "onm/grid-V`: `<field field_ref=\"voce\" name=\"vo\" operation=\"average\" freq_op=\"1mo\" > @voce_e3v / @e3v </field>",
    "HadGEM3-GC5": "onm/grid-V`: `<field field_ref=\"voce\" name=\"vo\" operation=\"average\" freq_op=\"1mo\" > @voce_e3v / @e3v </field>",
    "UKESM1": "onm/grid-V`: `<field field_ref=\"voce\" name=\"vo\" operation=\"average\" freq_op=\"1mo\" > @voce_e3v / @e3v </field>",
    "UKESM1-3": "onm/grid-V`: `<field field_ref=\"voce\" name=\"vo\" operation=\"average\" freq_op=\"1mo\" > @voce_e3v / @e3v </field>"
  },
  "Variable ocean.volcello.tavg-ol-hxy-sea.mon.GLB (Omon.volcello)": {
    "HadGEM3-GC31": "onm/grid-T`: `<field field_ref=\"e3t\" name=\"thkcello\" />",
    "HadGEM3-GC5": "onm/grid-T`: `<field field_ref=\"e3t\" name=\"thkcello\" />",
    "UKESM1": "onm/grid-T`: `<field field_ref=\"e3t\" name=\"thkcello\" />",
    "UKESM1-3": "onm/grid-T`: `<field field_ref=\"e3t\" name=\"thkcello\" />"
  },
  "Variable ocean.volcello.tavg-ol-hxy-sea.yr.GLB (Oyr.volcello)": {
    "HadGEM3-GC31": "onm/grid-T`: `<field field_ref=\"e3t\" name=\"thkcello\" />",
    "HadGEM3-GC5": "onm/grid-T`: `<field field_ref=\"e3t\" name=\"thkcello\" />",
    "UKESM1": "onm/grid-T`: `<field field_ref=\"e3t\" name=\"thkcello\" />",
    "UKESM1-3": "onm/grid-T`: `<field field_ref=\"e3t\" name=\"thkcello\" />"
  },
  "Variable ocean.volo.tavg-u-hm-sea.mon.GLB (Omon.volo)": {
    "HadGEM3-GC31": "onm/scalar`: `<field field_ref=\"voltot\" name=\"volo\" />",
    "HadGEM3-GC5": "onm/scalar`: `<field field_ref=\"voltot\" name=\"volo\" />",
    "UKESM1": "onm/scalar`: `<field field_ref=\"voltot\" name=\"volo\" />",
    "UKESM1-3": "onm/scalar`: `<field field_ref=\"voltot\" name=\"volo\" />"
  },
  "Variable ocean.vos.tavg-u-hxy-sea.day.GLB (Oday.vos)": {
    "HadGEM3-GC31": "ond/grid-V`: `<field field_ref=\"ssv\" name=\"vos\" />",
    "HadGEM3-GC5": "ond/grid-V`: `<field field_ref=\"ssv\" name=\"vos\" />",
    "UKESM1": "ond/grid-V`: `<field field_ref=\"ssv\" name=\"vos\" />",
    "UKESM1-3": "ond/grid-V`: `<field field_ref=\"ssv\" name=\"vos\" />"
  },
  "Variable ocean.wfo.tavg-u-hxy-sea.3hr.GLB (3hr.wfo)": {
    "HadGEM3-GC31": "on3/grid-T`: `<field field_ref=\"empmr\" name=\"wfo\" > -1 * (@empmr + @fwfisf) </field>",
    "HadGEM3-GC5": "on3/grid-T`: `<field field_ref=\"empmr\" name=\"wfo\" > -1 * (@empmr + @fwfisf) </field>",
    "UKESM1": "on3/grid-T`: `<field field_ref=\"empmr\" name=\"wfo\" > -1 * (@empmr + @fwfisf) </field>",
    "UKESM1-3": "on3/grid-T`: `<field field_ref=\"empmr\" name=\"wfo\" > -1 * (@empmr + @fwfisf) </field>"
  },
  "Variable ocean.wfo.tavg-u-hxy-sea.mon.GLB (Omon.wfo)": {
    "HadGEM3-GC31": "onm/grid-T`: `<field field_ref=\"empmr\" name=\"wfo\" > -1 * (@empmr + @fwfisf) </field>",
    "HadGEM3-GC5": "onm/grid-T`: `<field field_ref=\"empmr\" name=\"wfo\" > -1 * (@empmr + @fwfisf) </field>",
    "UKESM1": "onm/grid-T`: `<field field_ref=\"empmr\" name=\"wfo\" > -1 * (@empmr + @fwfisf) </field>",
    "UKESM1-3": "onm/grid-T`: `<field field_ref=\"empmr\" name=\"wfo\" > -1 * (@empmr + @fwfisf) </field>"
  },
  "Variable ocean.wmo.tavg-ol-hxy-sea.mon.GLB (Omon.wmo)": {
    "HadGEM3-GC31": "onm/grid-W`: `<field field_ref=\"w_masstr\" name=\"wmo\" detect_missing_value=\"true\"> @w_masstr + @weiv_masstr </field>",
    "HadGEM3-GC5": "onm/grid-W`: `<field field_ref=\"w_masstr\" name=\"wmo\" detect_missing_value=\"true\"> @w_masstr + @weiv_masstr </field>",
    "UKESM1": "onm/grid-W`: `<field field_ref=\"w_masstr\" name=\"wmo\" detect_missing_value=\"true\"> @w_masstr + @weiv_masstr </field>",
    "UKESM1-3": "onm/grid-W`: `<field field_ref=\"w_masstr\" name=\"wmo\" detect_missing_value=\"true\"> @w_masstr + @weiv_masstr </field>"
  },
  "Variable ocean.wo.tavg-ol-hxy-sea.day.GLB (Oday.wo)": {
    "HadGEM3-GC31": "ond/grid-W`: `<field field_ref=\"woce\" name=\"wo\" />",
    "HadGEM3-GC5": "ond/grid-W`: `<field field_ref=\"woce\" name=\"wo\" />",
    "UKESM1": "ond/grid-W`: `<field field_ref=\"woce\" name=\"wo\" />",
    "UKESM1-3": "ond/grid-W`: `<field field_ref=\"woce\" name=\"wo\" />"
  },
  "Variable ocean.wo.tavg-ol-hxy-sea.mon.GLB (Omon.wo)": {
    "HadGEM3-GC31": "onm/grid-W`: `<field field_ref=\"woce\" name=\"wo\" />",
    "HadGEM3-GC5": "onm/grid-W`: `<field field_ref=\"woce\" name=\"wo\" />",
    "UKESM1": "onm/grid-W`: `<field field_ref=\"woce\" name=\"wo\" />",
    "UKESM1-3": "onm/grid-W`: `<field field_ref=\"woce\" name=\"wo\" />"
  },
  "Variable ocean.zfullo.tavg-ol-hxy-sea.yr.GLB (Eyr.zfullo)": {
    "HadGEM3-GC31": "onm/grid-T`: `<field field_ref=\"tpt_dep\" name=\"zfullo\" />",
    "HadGEM3-GC5": "onm/grid-T`: `<field field_ref=\"tpt_dep\" name=\"zfullo\" />",
    "UKESM1": "onm/grid-T`: `<field field_ref=\"tpt_dep\" name=\"zfullo\" />",
    "UKESM1-3": "onm/grid-T`: `<field field_ref=\"tpt_dep\" name=\"zfullo\" />"
  },
  "Variable ocean.zos.tavg-u-hxy-sea.day.GLB (Oday.zos)": {
    "HadGEM3-GC31": "ond/grid-T`: `<field field_ref=\"sshdyn\" name=\"zos\" />",
    "HadGEM3-GC5": "ond/grid-T`: `<field field_ref=\"sshdyn\" name=\"zos\" />",
    "UKESM1": "ond/grid-T`: `<field field_ref=\"sshdyn\" name=\"zos\" />",
    "UKESM1-3": "ond/grid-T`: `<field field_ref=\"sshdyn\" name=\"zos\" />"
  },
  "Variable ocean.zos.tavg-u-hxy-sea.mon.GLB (Omon.zos)": {
    "HadGEM3-GC31": "onm/grid-T`: `<field field_ref=\"sshdyn\" name=\"zos\" />",
    "HadGEM3-GC5": "onm/grid-T`: `<field field_ref=\"sshdyn\" name=\"zos\" />",
    "UKESM1": "onm/grid-T`: `<field field_ref=\"sshdyn\" name=\"zos\" />",
    "UKESM1-3": "onm/grid-T`: `<field field_ref=\"sshdyn\" name=\"zos\" />"
  },
  "Variable ocean.zossq.tavg-u-hxy-sea.mon.GLB (Omon.zossq)": {
    "HadGEM3-GC31": "onm/grid-T`: `<field field_ref=\"sshdyn2\" name=\"zossq\" />",
    "HadGEM3-GC5": "onm/grid-T`: `<field field_ref=\"sshdyn2\" name=\"zossq\" />",
    "UKESM1": "onm/grid-T`: `<field field_ref=\"sshdyn2\" name=\"zossq\" />",
    "UKESM1-3": "onm/grid-T`: `<field field_ref=\"sshdyn2\" name=\"zossq\" />"
  },
  "Variable ocean.zostoga.tavg-u-hm-sea.day.GLB (Oday.zostoga)": {
    "HadGEM3-GC31": "ond/grid-T`: `<field field_ref=\"toce\" name=\"thetao\" operation=\"average\" freq_op=\"1d\" > @toce_e3t / @e3t </field>` <br> `ond/grid-T`: `<field field_ref=\"e3t\" name=\"thkcello\" />",
    "HadGEM3-GC5": "ond/grid-T`: `<field field_ref=\"toce_pot\" name=\"thetao\" operation=\"average\" freq_op=\"1d\" > @toce_pot_e3t / @e3t </field>` <br> `ond/grid-T`: `<field field_ref=\"e3t\" name=\"thkcello\" />",
    "UKESM1": "ond/grid-T`: `<field field_ref=\"toce\" name=\"thetao\" operation=\"average\" freq_op=\"1d\" > @toce_e3t / @e3t </field>` <br> `ond/grid-T`: `<field field_ref=\"e3t\" name=\"thkcello\" />",
    "UKESM1-3": "ond/grid-T`: `<field field_ref=\"toce\" name=\"thetao\" operation=\"average\" freq_op=\"1d\" > @toce_e3t / @e3t </field>` <br> `ond/grid-T`: `<field field_ref=\"e3t\" name=\"thkcello\" />"
  },
  "Variable ocean.zostoga.tavg-u-hm-sea.mon.GLB (Omon.zostoga)": {
    "HadGEM3-GC31": "onm/grid-T`: `<field field_ref=\"toce\" name=\"thetao\" operation=\"average\" freq_op=\"1mo\" > @toce_e3t / @e3t </field>` <br> `onm/grid-T`: `<field field_ref=\"e3t\" name=\"thkcello\" />",
    "HadGEM3-GC5": "onm/grid-T`: `<field field_ref=\"toce_pot\" name=\"thetao\" operation=\"average\" freq_op=\"1mo\" > @toce_pot_e3t / @e3t </field>` <br> `onm/grid-T`: `<field field_ref=\"e3t\" name=\"thkcello\" />",
    "UKESM1": "onm/grid-T`: `<field field_ref=\"toce\" name=\"thetao\" operation=\"average\" freq_op=\"1mo\" > @toce_e3t / @e3t </field>` <br> `onm/grid-T`: `<field field_ref=\"e3t\" name=\"thkcello\" />",
    "UKESM1-3": "onm/grid-T`: `<field field_ref=\"toce\" name=\"thetao\" operation=\"average\" freq_op=\"1mo\" > @toce_e3t / @e3t </field>` <br> `onm/grid-T`: `<field field_ref=\"e3t\" name=\"thkcello\" />"
  },
  "Variable seaIce.siconc.tavg-u-hxy-u.day.GLB (SIday.siconc)": {
    "HadGEM3-GC5": "ind/grid-T`: `<field field_ref=\"iceconc\" name=\"siconc\" />"
  },
  "Variable seaIce.siflcondbot.tavg-u-hxy-si.day.GLB (SIday.siflcondbot)": {
    "HadGEM3-GC5": "ind/grid-T`: `<field field_ref=\"iceconc\" name=\"siconc\" />` <br> `ind/grid-T`: `<field id=\"hfxcndbot\"    long_name=\"Net conductive heat flux at the ice bottom (neg = ice cooling)\"   standard_name=\"conductive_heat_flux_at_sea_ice_bottom\"     unit=\"W/m2\" />"
  },
  "Variable seaIce.siflcondtop.tavg-u-hxy-si.day.GLB (SIday.siflcondtop)": {
    "HadGEM3-GC5": "ind/grid-T`: `<field field_ref=\"iceconc\" name=\"siconc\" />` <br> `ind/grid-T`: `<field id=\"hfxcndtop\"    long_name=\"Net conductive heat flux at the ice surface (neg = ice cooling)\"  standard_name=\"conductive_heat_flux_at_sea_ice_surface\"    unit=\"W/m2\" />"
  },
  "Variable seaIce.sifllattop.tavg-u-hxy-si.day.GLB (SIday.sifllattop)": {
    "HadGEM3-GC5": "ind/grid-T`: `<field field_ref=\"iceconc\" name=\"siconc\" />` <br> `ind/grid-T`: `<field id=\"hfxsub\"       long_name=\"heat fluxes from ice-atm. mass exchange during sublimation\"   unit=\"W/m2\" />"
  },
  "Variable seaIce.siflsensbot.tavg-u-hxy-si.day.GLB (SIday.siflsensbot)": {
    "HadGEM3-GC5": "ind/grid-T`: `<field field_ref=\"iceconc\" name=\"siconc\" />` <br> `ind/grid-T`: `<field id=\"hfxsensib\"    long_name=\"Net sensible heat flux under sea ice (neg = ice cooling)\"         standard_name=\"ice_ocean_heat_flux\"                        unit=\"W/m2\" />"
  },
  "Variable seaIce.siflswdbot.tavg-u-hxy-si.day.GLB (SIday.siflswdbot)": {
    "HadGEM3-GC5": "ind/grid-T`: `<field field_ref=\"iceconc\" name=\"siconc\" />` <br> `ind/grid-T`: `<field id=\"qtr_ice_bot\"  long_name=\"solar heat flux transmitted through the ice (to the ocean)\" unit=\"W/m2\" />"
  },
  "Variable seaIce.sihc.tavg-u-hxy-sea.day.GLB (SIday.sihc)": {
    "HadGEM3-GC5": "ind/grid-T` : `<field field_ref=\"icehc_cmip\"       name=\"sihc\"         />"
  }
}